<?xml version="1.0" encoding="UTF-8"?>

<dialogs>
    <dia pl="0" str="Seu pai me enviou. Você sabe por que o leite que você vende é azedo?"/>
    <dia npc="0" str="Azedo? Pai? Eu não sei do que você está falando. Esse leite aqui está bom."/>
    <dia pl="1_0" str="Tudo bem filho. Não há necessidade de ficar alarmado. Tenho certeza de que foi um erro. Vou deixar você com seu trabalho." jumpNPCd= "0" jumpPlayerd = '0'/>
    <dia pl="1_1" str="Ouça aqui, garoto. Algo está errado com o leite que você vende. Seu pai parecia muito chateado com isso."/>
    <dia npc="1" str="Posso ter esquecido de limpar as batedeiras algumas vezes."/>
    <dia pl="2" str="O que devo fazer com você agora? Devo contar ao seu pai sobre isso?"/>
    <dia npc="2" str="Por favor, não conte ao pai! Ele me mandaria de volta para manter a igreja limpa. Essa igreja é enorme. Eu prometo que vou trabalhar mais. Vou manter as batedeiras limpas!"/>
	<dia pl="3" str="Mantenha as batedeiras limpas e você não terá que voltar para a igreja. Você deveria começar agora mesmo, antes que seu pai venha aqui." jumpNPCd= "0" jumpPlayerd = '0'/>
</dialogs>
